{"next":"/v1/catalog/us/apps/1135325440/reviews?l=en-US&offset=93290","data":[{"id":"6176781156","type":"user-reviews","attributes":{"date":"2020-07-09T13:46:51Z","rating":1,"review":"unfortunately, this app supports a racist, homophobic, sexist man who has somehow become our president (abolish the electoral college❤️).","userName":"Flowergirl10101010","isEdited":false,"title":"poor quality"}},{"id":"6176728443","type":"user-reviews","attributes":{"date":"2020-07-09T13:32:55Z","rating":1,"review":"Horrible app","userName":"Idk everything else is taken","isEdited":false,"title":"Horrible"}},{"id":"6176726148","type":"user-reviews","attributes":{"date":"2020-07-09T13:32:20Z","rating":1,"review":"Just bad there is no purpose of it","userName":"who to the dishwasher","isEdited":false,"title":"Bad"}},{"id":"6176705892","type":"user-reviews","attributes":{"date":"2020-07-09T13:27:00Z","rating":1,"review":"This app is super sketchy would not recommend.","userName":"uteskyrskyf","isEdited":false,"title":"DO NOT DOWNLOAD"}},{"id":"6176680555","type":"user-reviews","attributes":{"date":"2020-07-09T13:20:22Z","rating":1,"review":"this is a racist white supremacist app. worst app i’ve ever seen. makes me want to vomit. it makes me sick to my stomach. abolish the police.","userName":"laur3nyoung","isEdited":false,"title":"you are stupid"}},{"id":"6176679997","type":"user-reviews","attributes":{"date":"2020-07-09T13:20:13Z","rating":1,"review":"this app literally came to life and killed my entire family","userName":"jxkdjenckdkensjakf","isEdited":false,"title":"trump has small pp"}},{"id":"6176678059","type":"user-reviews","attributes":{"date":"2020-07-09T13:19:42Z","rating":1,"review":"And by faulty I mean the system ran by the president not the app 😌","userName":"Iloveitwhentheycallmebigpoppa","isEdited":false,"title":"Very faulty"}},{"id":"6176676968","type":"user-reviews","attributes":{"date":"2020-07-09T13:19:25Z","rating":1,"review":"Where my Mexican neighbors go?","userName":"LongDingDongslongchongKlong","isEdited":false,"title":"😘"}},{"id":"6176655056","type":"user-reviews","attributes":{"date":"2020-07-09T13:13:37Z","rating":1,"review":"Took forever to load then forced me to vote for trump","userName":"crappy iron god","isEdited":false,"title":"Horibble"}},{"id":"6176654115","type":"user-reviews","attributes":{"date":"2020-07-09T13:13:23Z","rating":1,"review":"Yeah no. This app is terrible and unnecessary. Just like our president.","userName":"gravity falls on crack","isEdited":false,"title":"Lol"}}]}