{"next":"/v1/catalog/us/apps/1135325440/reviews?l=en-US&offset=125180","data":[{"id":"6172394184","type":"user-reviews","attributes":{"date":"2020-07-08T14:07:25Z","title":"Por k puedo","rating":1,"isEdited":false,"review":"Vas a borrar una que un montón de personas aman so borramos tu app 8)","userName":"otakuOwO"}},{"id":"6172389035","type":"user-reviews","attributes":{"date":"2020-07-08T14:06:03Z","title":"Just no","rating":1,"isEdited":false,"review":"Educate you self ... just no","userName":"jusy o"}},{"id":"6172383075","type":"user-reviews","attributes":{"date":"2020-07-08T14:04:30Z","title":"BLM","rating":1,"isEdited":false,"review":"No just no","userName":"prince3888888888888889"}},{"id":"6172377515","type":"user-reviews","attributes":{"date":"2020-07-08T14:03:02Z","title":"Spring day -BTS 💜✨🏳️\u200D🌈💫","rating":1,"isEdited":false,"review":"보고 싶다\n이렇게 말하니까 더\n보고 싶다\n너희 사진을 보고 있어도\n보고 싶다\n너무 야속한 시간\n나는 우리가 밉다\n이젠 얼굴 한 번 보는 것도\n힘들어진 우리가\n여긴 온통 겨울 뿐이야\n8월에도 겨울이 와\n마음은 시간을 달려가네\n홀로 남은 설국열차\n니 손 잡고\n지구 반대편까지 가\n겨울을 끝내고파\n그리움들이 얼마나 눈처럼 내려야\n그 봄날이 올까\nFriend\n허공을 떠도는 작은 먼지처럼\n작은 먼지처럼\n날리는 눈이 나라면\n조금 더 빨리 네게\n닿을 수 있을 텐데\n눈꽃이 떨어져요\n또 조금씩 멀어져요\n보고 싶다 (보고 싶다)\n보고 싶다 (보고 싶다)\n얼마나 기다려야\n또 몇 밤을 더 새워야\n널 보게 될까 (널 보게 될까)\n만나게 될까 (만나게 될까)\n추운 겨울 끝을 지나\n다시 봄날이 올 때까지\n꽃 피울 때까지\n그곳에 좀 더 머물러줘\n머물러줘\n니가 변한 건지\n(니가 변한 건지)\n아니면 내가 변한 건지\n(내가 변한 건지)\n이 순간 흐르는 시간조차 미워\n우리가 변한 거지 뭐\n모두가 그런 거지 뭐\n그래 밉다 니가\n넌 떠났지만\n단 하루도 너를\n잊은 적이 없었지 난\n솔직히 보고 싶은데\n이만 너를 지울게\n그게 널 원망하기보단 덜 아프니까\n시린 널 불어내 본다\n연기처럼 하얀 연기처럼\n말로는 지운다 해도\n사실 난 아직 널 보내지 못하는데\n눈꽃이 떨어져요\n또 조금씩 멀어져요\n보고 싶다 (보고 싶다)","userName":"maknae/mae"}},{"id":"6172375920","type":"user-reviews","attributes":{"date":"2020-07-08T14:02:37Z","title":"Tiktok","rating":1,"isEdited":false,"review":"From tiktok","userName":"lanesuana"}},{"id":"6172366587","type":"user-reviews","attributes":{"date":"2020-07-08T14:00:05Z","title":"Bad juju","rating":1,"isEdited":false,"review":"hurt my feelings 😔","userName":"subject52"}},{"id":"6172354808","type":"user-reviews","attributes":{"date":"2020-07-08T13:56:52Z","title":"No ❤️","rating":1,"isEdited":false,"review":"No ❤️ No ❤️ No ❤️ No ❤️ No ❤️ No ❤️ No ❤️ No ❤️ No ❤️ No ❤️ No ❤️ No ❤️ No ❤️ No ❤️ No ❤️ No ❤️ No ❤️ No ❤️ No ❤️ No ❤️ No ❤️ No ❤️ No ❤️ No ❤️ No ❤️ No ❤️ No ❤️ No ❤️ No ❤️ No ❤️ No ❤️ No ❤️ No ❤️ No ❤️ No ❤️ No ❤️ No ❤️ No ❤️ No ❤️ No ❤️ No ❤️ No ❤️ No ❤️ No ❤️ No ❤️ No ❤️ No ❤️ No ❤️ No ❤️ No ❤️ No ❤️ No ❤️ No ❤️ No ❤️ No ❤️ No ❤️ No ❤️ No ❤️ No ❤️ No ❤️ No ❤️ No ❤️ No ❤️ No ❤️ No ❤️ No ❤️ No ❤️ No ❤️ No ❤️ No ❤️ No ❤️ No ❤️ No ❤️ No ❤️ No ❤️ No ❤️ No ❤️ No ❤️ No ❤️ No ❤️  No ❤️ No ❤️ No ❤️ No ❤️ No ❤️ No ❤️ No ❤️ No ❤️ No ❤️ No ❤️ No ❤️ No ❤️ No ❤️ No ❤️ No ❤️ No ❤️ No ❤️ No ❤️ No ❤️ No ❤️ No ❤️ No ❤️ No ❤️ No ❤️ No ❤️ No ❤️ No ❤️ No ❤️ No ❤️ No ❤️ No ❤️ No ❤️ No ❤️ No ❤️ No ❤️ No ❤️ No ❤️ No ❤️ No ❤️ No ❤️ No ❤️ No ❤️ No ❤️ No ❤️ No ❤️ No ❤️ No ❤️  No ❤️ No ❤️ No ❤️ No ❤️ No ❤️ No ❤️ No ❤️ No ❤️ No ❤️ No ❤️ No ❤️ No ❤️ No ❤️ No ❤️ No ❤️ No ❤️ No ❤️ No ❤️ No ❤️ No ❤️ No ❤️ No ❤️ No ❤️ No ❤️ No ❤️ No ❤️ No ❤️ No ❤️ No ❤️ No ❤️ No ❤️ No ❤️ No ❤️ No ❤️ No ❤️ No ❤️ No ❤️ No ❤️ No ❤️ No ❤️ No ❤️ No ❤️ No ❤️ No ❤️ No ❤️ No ❤️ No ❤️ No ❤️ No ❤️ No ❤️ No ❤️ No ❤️ No ❤️","userName":"A Random Dog Lover"}},{"id":"6172348955","type":"user-reviews","attributes":{"date":"2020-07-08T13:55:15Z","title":"Bad","rating":1,"isEdited":false,"review":"Bad bad bad","userName":"IzzyFizzyLizzie"}},{"id":"6172344221","type":"user-reviews","attributes":{"date":"2020-07-08T13:53:58Z","title":"We don’t Stan","rating":1,"isEdited":false,"review":"내 피 땀 눈물\n내 마지막 춤을\n다 가져가 가\n내 피 땀 눈물\n내 차가운 숨을\n다 가져가 가\n내 피 땀 눈물\n내 피 땀 눈물도\n내 몸 마음 영혼도\n너의 것인 걸 잘 알고 있어\n이건 나를 벌받게 할 주문\n\nPeaches and cream\nSweeter than sweet\nChocolate cheeks\nAnd chocolate wings\nBut 너의 날개는 악마의 것\n너의 그 sweet 앞엔 bitter bitter\n\nKiss me 아파도 돼\n어서 날 조여줘\n더 이상 아플 수도 없게\nBaby 취해도 돼 이제 널 들이켜\n목 깊숙이 너란 위스키\n\n내 피 땀 눈물\n내 마지막 춤을\n다 가져가 가\n내 피 땀 눈물\n내 차가운 숨을\n다 가져가 가\n\n원해 많이 많이 많이 많이\n원해 많이 많이 많이 많이 많이 많이\n원해 많이 많이 많이 많이\n원해 많이 많이 많이 많이 많이 많이\n\n아파도 돼 날 묶어줘\n내가 도망칠 수 없게\n꽉 쥐고 날 흔들어줘\n내가 정신 못 차리게\nKiss me on the lips lips\n둘만의 비밀\n너란 감옥에 중독돼 깊이\n니가 아닌 다른 사람 섬기지 못해\n알면서도 삼켜버린\n독이 든 성배\n\n내 피 땀 눈물\n내 마지막 춤을\n다 가져가 가\n내 피 땀 눈물\n내 차가운 숨을\n다 가져가 가\n\n원해 많이 많이 많이 많이\n원해 많이 많이 많이 많이 많이 많이\n원해 많이 많이 많이 많이\n원해 많이 많이 많이 많이 많이 많이\n\n나를 부드럽게 죽여줘\n너의 손길로 눈 감겨줘\n어차피 거부할 수조차 없어\n더는 도망갈 수조차 없어\n니가 너무 달콤해 너무 달콤해\n너무 달콤해서\n\n내 피 땀 눈물\n내 피 땀 눈물","userName":"🧚💖🌸"}},{"id":"6172342503","type":"user-reviews","attributes":{"date":"2020-07-08T13:53:29Z","title":"Oranges.🤮","rating":1,"isEdited":false,"review":"I dont- i dont like- I DONT LIKE ORANGES. 🤢🤮🍊🍊😭🤢🤮✌🏽🥵","userName":"i dont like paper.io"}}]}