{"next":"/v1/catalog/us/apps/1135325440/reviews?l=en-US&offset=98180","data":[{"id":"6178094261","type":"user-reviews","attributes":{"date":"2020-07-09T20:14:58Z","review":"causes my phone to glitch","isEdited":false,"userName":"heknrndjd","rating":1,"title":"👎🏾"}},{"id":"6178080320","type":"user-reviews","attributes":{"date":"2020-07-09T20:10:23Z","review":"Why would anyone be this stupid to vote for a clown ☺️✨","isEdited":false,"userName":"Meybaline","rating":1,"title":"The WORST THING EVER"}},{"id":"6178076961","type":"user-reviews","attributes":{"date":"2020-07-09T20:09:13Z","review":"horrible app horrible person horrible president. yeah❤️","isEdited":false,"userName":"Mariela Gisselle","rating":1,"title":"glitchy"}},{"id":"6178071758","type":"user-reviews","attributes":{"date":"2020-07-09T20:07:34Z","review":"This app stole all my info and hacked ALL my accounts UNACCEPTABLE‼️","isEdited":false,"userName":"ä19","rating":1,"title":"Scam likely⚠️"}},{"id":"6178064702","type":"user-reviews","attributes":{"date":"2020-07-09T20:05:14Z","review":"#black lives matter periodttttt","isEdited":false,"userName":"Ky'Arra","rating":1,"title":"Orange man"}},{"id":"6178063992","type":"user-reviews","attributes":{"date":"2020-07-09T20:04:59Z","review":"This app has no purpose but to promote satan.","isEdited":false,"userName":"dfhuaivksk","rating":1,"title":"Disturbing"}},{"id":"6178045504","type":"user-reviews","attributes":{"date":"2020-07-09T19:58:58Z","review":"I hate the app it’s stupid","isEdited":false,"userName":"omg nasty12345","rating":1,"title":"He smells like Cheeto puffs"}},{"id":"6178042937","type":"user-reviews","attributes":{"date":"2020-07-09T19:58:06Z","review":"This app is just a no no","isEdited":false,"userName":"Applesoberklidw","rating":1,"title":"Trash"}},{"id":"6178027661","type":"user-reviews","attributes":{"date":"2020-07-09T19:53:08Z","review":"just as the president this app is trash","isEdited":false,"userName":"orangefacesmalldick","rating":1,"title":"HORRIBLE"}},{"id":"6178020339","type":"user-reviews","attributes":{"date":"2020-07-09T19:50:40Z","review":"It’s terrible. That’s it that’s my review","isEdited":false,"userName":"jehsvsh","rating":1,"title":"Boo boo"}}]}