{"next":"/v1/catalog/us/apps/1135325440/reviews?l=en-US&offset=98280","data":[{"id":"6176062079","type":"user-reviews","attributes":{"review":"This app is terrible do not download","rating":1,"userName":"shhdhdhdhdha","title":"This is for tiktok👌🔥😎","date":"2020-07-09T10:22:15Z","isEdited":false}},{"id":"6176052229","type":"user-reviews","attributes":{"review":"why is this app even allowed?? IT DOESNT EVEN WORK","rating":1,"userName":"😔✨💓","title":"yolofroyo","date":"2020-07-09T10:19:04Z","isEdited":false}},{"id":"6176021868","type":"user-reviews","attributes":{"review":"Omg so bad not good president bad omg","rating":1,"userName":"DrewRuos","title":"He is, can’t believe it","date":"2020-07-09T10:09:20Z","isEdited":false}},{"id":"6175976384","type":"user-reviews","attributes":{"review":"I hated it","rating":1,"userName":"steve678999831","title":"This app is awful","date":"2020-07-09T09:54:44Z","isEdited":false}},{"id":"6175942160","type":"user-reviews","attributes":{"review":"Terrible app for Terrible human","rating":1,"userName":"orjci lflsjxividmsbsjs","title":"Terrible","date":"2020-07-09T09:43:34Z","isEdited":false}},{"id":"6175866198","type":"user-reviews","attributes":{"review":"It took my first born son","rating":1,"userName":"Malcatacorn","title":"Horrible 🤬🤬","date":"2020-07-09T09:18:02Z","isEdited":false}},{"id":"6175857167","type":"user-reviews","attributes":{"review":"This is the absolute worst app I ever had🤮Estúpida","rating":1,"userName":"arozona tea","title":"Worst app ever","date":"2020-07-09T09:15:02Z","isEdited":false}},{"id":"6175786820","type":"user-reviews","attributes":{"review":"this is the WORST app i’ve ever downloaded. THIS APP SHOULD BE BANNED FROM THE US","rating":1,"userName":"Janine Hartman","title":"disgusting","date":"2020-07-09T08:51:34Z","isEdited":false}},{"id":"6175777334","type":"user-reviews","attributes":{"review":"I just don't think so 🥰💞","rating":1,"userName":"edgyboiyo","title":"No🥰","date":"2020-07-09T08:48:12Z","isEdited":false}},{"id":"6175693703","type":"user-reviews","attributes":{"review":"i think we are all here from tiktok","rating":1,"userName":"jorje193846","title":"terrible app","date":"2020-07-09T08:19:40Z","isEdited":false}}]}