{"next":"/v1/catalog/us/apps/1135325440/reviews?l=en-US&offset=102670","data":[{"id":"6173975703","type":"user-reviews","attributes":{"rating":1,"userName":"big booty booty judy","title":"no❤️.","review":"this app is horrible, why is it horrible? because of this stink cheeto😘.","date":"2020-07-08T22:39:01Z","isEdited":false}},{"id":"6173975681","type":"user-reviews","attributes":{"rating":1,"userName":"j.f.cktrump","title":"Disgusting.","review":"Most disgusting porn website and seen TAKE IT OFF & BAN IT NEEEOOOWWWW🍅","date":"2020-07-08T22:39:01Z","isEdited":false}},{"id":"6173968775","type":"user-reviews","attributes":{"rating":1,"userName":"follow my tiktok papa_stanley","title":"Bad glitch","review":"It glitched really bad","date":"2020-07-08T22:36:23Z","isEdited":false}},{"id":"6173947382","type":"user-reviews","attributes":{"rating":1,"userName":"Pickywithapps","title":"Just no","review":"Worst app ever","date":"2020-07-08T22:28:19Z","isEdited":false}},{"id":"6173940378","type":"user-reviews","attributes":{"rating":1,"userName":"emilyev1992","title":"Garbage","review":"This app is weak and so is the platform.","date":"2020-07-08T22:25:41Z","isEdited":false}},{"id":"6173938277","type":"user-reviews","attributes":{"rating":1,"userName":"trump 2020 on a ✨gravestone✨","title":"terrible","review":"this app is so so so bad because two+cow=tree","date":"2020-07-08T22:24:57Z","isEdited":false}},{"id":"6173934523","type":"user-reviews","attributes":{"rating":1,"userName":"Hollyh77","title":"bad❤️","review":"very, very bad. runs as slow as his brain ☺️","date":"2020-07-08T22:23:30Z","isEdited":false}},{"id":"6173905768","type":"user-reviews","attributes":{"rating":1,"userName":"jdbjdjfiejdjxujdjjjj","title":"this was not it.","review":"it was a sight. that i cannot get outta my head.","date":"2020-07-08T22:13:01Z","isEdited":false}},{"id":"6173905445","type":"user-reviews","attributes":{"rating":1,"userName":"friffen18394","title":"bad app","review":"donald trump said he only likes people that aren’t colored!!","date":"2020-07-08T22:12:54Z","isEdited":false}},{"id":"6173901856","type":"user-reviews","attributes":{"rating":1,"userName":"dkshjsbs","title":"Horrible","review":"It made me gag","date":"2020-07-08T22:11:35Z","isEdited":false}}]}