{"next":"/v1/catalog/us/apps/1135325440/reviews?l=en-US&offset=114620","data":[{"id":"6178004320","type":"user-reviews","attributes":{"isEdited":false,"date":"2020-07-09T19:45:24Z","title":"WHAT THE ——","rating":1,"review":"MY APP KEEPS CRASHING AND GOING STRAIGHT TO TIK TOK.... STARTING TO THINK ITS BECAUSE I GOT A NEW PHONE. WE NEED UPDATES NOW...😬","userName":"Keila!!!!"}},{"id":"6177987543","type":"user-reviews","attributes":{"isEdited":false,"date":"2020-07-09T19:39:56Z","title":"Bad","rating":1,"review":"This app bad.","userName":"trump supporterrr"}},{"id":"6177922846","type":"user-reviews","attributes":{"isEdited":false,"date":"2020-07-09T19:18:54Z","title":"Blehhh 🤢🤮🤢","rating":1,"review":"Bleh 🤢🤮 the annoying orange 🍊","userName":"GirlWithAHydro"}},{"id":"6177921386","type":"user-reviews","attributes":{"isEdited":false,"date":"2020-07-09T19:18:26Z","title":"no","rating":1,"review":"mr orange did a bad job","userName":"mr krabs 2.0"}},{"id":"6177699948","type":"user-reviews","attributes":{"isEdited":false,"date":"2020-07-09T18:10:40Z","title":"H","rating":1,"review":"App is really bad","userName":"purge777"}},{"id":"6177698240","type":"user-reviews","attributes":{"isEdited":false,"date":"2020-07-09T18:10:10Z","title":"DONALD GÆ TRUMP IS RACIST AND STUPID","rating":1,"review":"Trash also got this from tik tok","userName":"Trump is gæ"}},{"id":"6177572949","type":"user-reviews","attributes":{"isEdited":false,"date":"2020-07-09T17:30:07Z","title":"💜BTS Fake love lyrics💜","rating":1,"review":"널 위해서라면 난 슬퍼도 기쁜 척 할 수가 있었어\n널 위해서라면 난 아파도 강한 척 할 수가 있었어\n사랑이 사랑만으로 완벽하길\n내 모든 약점들은 다 숨겨지길\n이뤄지지 않는 꿈속에서 피울 수 없는 꽃을 키웠어\nI'm so sick of this fake love, fake love, fake love\nI'm so sorry but it's fake love, fake love, fake love\nI wanna be a good man just for you\n세상을 줬네 just for you\n전부 바꿨어 just for you\nNow I don't know me, who are you?\nHi, 우리만의 숲 너는 없었어\n내가 왔던 route 잊어버렸어\n나도 내가 누구였는지도 잘 모르게 됐어\n거울에다 지껄여봐 너는 대체 누구니\n널 위해서라면 난 슬퍼도 기쁜 척 할 수가 있었어\n널 위해서라면 난 아파도 강한 척 할 수가 있었어\n사랑이 사랑만으로 완벽하길\n내 모든 약점들은 다 숨겨지길\n이뤄지지 않는 꿈속에서 피울 수 없는 꽃을 키웠어\nLove you so bad, love you so bad\n널 위해 예쁜 거짓을 빚어내\nLove you so mad, love you so mad\n날 지워 너의 인형이 되려 해\nLove you so bad, love you so bad\n널 위해 예쁜 거짓을 빚어내\nLove you so mad, love you so mad\n날 지워 너의 인형이 되려 해\nI'm so sick of this fake love, fake love, fake love\nI'm so sorry but it's fake love, fake love, fake love\nWhy you sad? I don't know 난 몰라\n웃어봐 사랑해 말해봐\n나를 봐 나조차도 버린 나\n너조차 이해할 수 없는 나\n낯설다 하네 니가 좋아하던 나로 변한 내가\n아니라 하네 예전에 니가 잘 알고 있던 내가\n아니긴 뭐가 아냐 난 눈 멀었어\n사랑은 뭐가 사랑 it's all fake love\nI don't know, I don't know, I don't know why\n(Woo) 나도 날 나도 날 모르겠어\n(Woo) I just know, I just know, I just know why\n'Cause its all fake love, fake love, fake love\nLove you so bad, love you so bad\n널 위해 예쁜 거짓을 빚어내\nLove you so mad, love you so mad\n날 지워 너의 인형이 되려 해\nLove you so bad, love you so bad\n널 위해 예쁜 거짓을 빚어내\nLove you so mad, love you so mad\n날 지워 너의 인형이 되려 해\nI'm so sick of this fake love, fake love, fake love\nI'm so sorry but it's fake love, fake love, fake love\n널 위해서라면 난 슬퍼도 기쁜 척 할 수가 있었어\n널 위해서라면 난 아파도 강한 척 할 수가 있었어\n사랑이 사랑만으로 완벽하길\n내 모든 약점들은 다 숨겨지길 \n이뤄지지 않는 꿈속에서 피울 수 없는 꽃을 키웠어","userName":"What is life12345678910"}},{"id":"6177532096","type":"user-reviews","attributes":{"isEdited":false,"date":"2020-07-09T17:17:14Z","title":"Terrible","rating":1,"review":"Frick trump 😤","userName":"@zedlover"}},{"id":"6177385376","type":"user-reviews","attributes":{"isEdited":false,"date":"2020-07-09T16:33:12Z","title":"Horrible 🧚\u200D♀️🧚\u200D♂️🧚💖🔫🎀","rating":1,"review":"😀 😃 😄 😁 😆 🤩 😅 😂 🤣 ☺️ 😊 😇 🙂 🙃 😉 😌 😍 😘 😗 😙 😚 😋 🤪 😜 😝 😛 🤑 🤗 🤓 😎 🤡 🤠 😏 😒 😞 😔 😟 😕 🙁 ☹️ 😣 😖 😫 😩 😤 😠 😡 🤬 😶 😐 😑 😯 😦 😧 😮 😲 😵 🤯 😳 😱 😨 😰 😢 😥 🤤 😭 😓 😪 😴 🥱 🙄 🤨 🧐 🤔 🤫 🤭 🤥 😬 🤐 🤢 🤮 🤧 😷 🤒 🤕 😈 👿 👹 👺 💩 👻 💀 ☠️ 👽 👾 🤖 🎃 😺 😸 😹 😻 😼 😽 🙀 😿 😾 👐 🙌 👏 🙏 🤲 🤝 👍 👎 👊 ✊ 🤛 🤜 🤞 ✌️ 🤘 🤏 👌 👈 👉 👆 👇 ☝️ ✋ 🤚 🖐 🖖 👋 🤙 💪 🖕 🤟 ✍️ 🤳 💅 🖖 💄 💋 👄 👅 👂 🦻 👃 🦵 🦶 🦾 🦿 👣 👁 👀 🗣 👤 👥 👶 👦 👧 🧒 👨 👩 🧑 👱\u200D♀️ 👱 🧔 👴 👵 🧓 👲 👳\u200D♀️ 👳 🧕 👮\u200D♀️ 👮 👷\u200D♀️ 👷 💂\u200D♀️ 💂 🕵️\u200D♀️ 🕵️ 👩\u200D⚕️ 👨\u200D⚕️ 👩\u200D🌾 👨\u200D🌾 👩\u200D🍳 👨\u200D🍳 👩\u200D🎓 👨\u200D🎓 👩\u200D🎤 👨\u200D🎤 👩\u200D🏫 👨\u200D🏫 👩\u200D🏭 👨\u200D🏭 👩\u200D💻 👨\u200D💻 👩\u200D💼 👨\u200D💼 👩\u200D🔧 👨\u200D🔧 👩\u200D🔬 👨\u200D🔬 👩\u200D🎨 👨\u200D🎨 👩\u200D🚒 👨\u200D🚒 👩\u200D✈️ 👨\u200D✈️ 👩\u200D🚀 👨\u200D🚀 👩\u200D⚖️ 👨\u200D⚖️ 🤶 🎅 👸 🤴 👰 🤵 👼 🤰 🤱 🙇\u200D♀️ 🙇 💁 💁\u200D♂️ 🙅 🙅\u200D♂️ 🙆 🙆\u200D♂️ 🙋 🙋\u200D♂️ 🤦\u200D♀️ 🤦\u200D♂️ 🤷\u200D♀️ 🤷\u200D♂️ 🙎 🙎\u200D♂️ 🙍 🙍\u200D♂️ 💇 💇\u200D♂️ 💆 💆\u200D♂️ 🧖\u200D♀️ 🧖\u200D♂️ 🧏 🧏\u200D♂️ 🧏\u200D♀️ 🧙\u200D♀️ 🧙\u200D♂️ 🧛\u200D♀️ 🧛\u200D♂️ 🧟\u200D♀️ 🧟\u200D♂️ 🧚\u200D♀️ 🧚\u200D♂️ 🧜\u200D♀️ 🧜\u200D♂️ 🧝\u200D♀️ 🧝\u200D♂️ 🧞\u200D♀️ 🧞\u200D♂️ 🕴 💃 🕺 👯 👯\u200D♂️ 🚶\u200D♀️ 🚶 🏃\u200D♀️ 🏃 🧍 🧍\u200D♂️ 🧍\u200D♀️ 🧎 🧎\u200D♂️ 🧎\u200D♀️ 👨\u200D🦯 👩\u200D🦯 👨\u200D🦼 👩\u200D🦼 👨\u200D🦽 👩\u200D🦽 🧑\u200D🤝\u200D🧑 👫 👭 👬 💑 👩\u200D❤️\u200D👩 👨\u200D❤️\u200D👨 💏 👩\u200D❤️\u200D💋\u200D👩 👨\u200D❤️\u200D💋\u200D👨 👪 👨\u200D👩\u200D👧 👨\u200D👩\u200D👧\u200D👦 👨\u200D👩\u200D👦\u200D👦 👨\u200D👩\u200D👧\u200D👧 👩\u200D👩\u200D👦 👩\u200D👩\u200D👧 👩\u200D👩\u200D👧\u200D👦 👩\u200D👩\u200D👦\u200D👦 👩\u200D👩\u200D👧\u200D👧 👨\u200D👨\u200D👦 👨\u200D👨\u200D👧 👨\u200D👨\u200D👧\u200D👦 👨\u200D👨\u200D👦\u200D👦 👨\u200D👨\u200D👧\u200D👧 👩\u200D👦 👩\u200D👧 👩\u200D👧\u200D👦 👩\u200D👦\u200D👦 👩\u200D👧\u200D👧 👨\u200D👦 👨\u200D👧 👨\u200D👧\u200D👦 👨\u200D👦\u200D👦 👨\u200D👧\u200D👧 👚 👕 👖 👔 👗 👙 👘 👠 👡 👢 👞 👟 👒 🎩 🎓 👑 ⛑ 🎒 👝 👛 👜 💼 👓 🕶 🤿 🌂 ☂️ 🧣 🧤 🧥 🦺 🥻 🩱 🩲 🩳 🩰 🧦 🧢 ⛷ 🏂 🏋️\u200D♀️ 🏋️ 🤺 🤼\u200D♀️ 🤼\u200D♂️ 🤸\u200D♀️ 🤸\u200D♂️ ⛹️\u200D♀️ ⛹️ 🤾\u200D♀️ 🤾\u200D♂️ 🏌️\u200D♀️ 🏌️ 🏄\u200D♀️ 🏄 🏊\u200D♀️ 🏊 🤽\u200D♀️ 🤽\u200D♂️ 🚣\u200D♀️ 🚣 🏇 🚴\u200D♀️ 🚴 🚵\u200D♀️ 🚵 🤹\u200D♀️ 🤹\u200D♂️ 🧗\u200D♀️ 🧗\u200D♂️ 🧘\u200D♀️ 🧘\u200D♂️ 🥰 🥵 🥶 🥳 🥴 🥺 🦸 🦹 🧑\u200D🦰 🧑\u200D🦱 🧑\u200D🦳 🧑\u200D🦲 🧑\u200D⚕️ 🧑\u200D🎓 🧑\u200D🏫 🧑\u200D⚖️ 🧑\u200D🌾 🧑\u200D🍳 🧑\u200D🔧 🧑\u200D🏭 🧑\u200D💼 🧑\u200D🔬 🧑\u200D💻 🧑\u200D🎤 🧑\u200D🎨 🧑\u200D✈️ 🧑\u200D🚀 🧑\u200D🚒 🧑\u200D🦯 🧑\u200D🦼 🧑\u200D🦽 🦰 🦱 🦲 🦳 🐶 🐱 🐭 🐹 🐰 🦊 🐻 🐼 🐨 🐯 🦁 🐮 🐷 🐽 🐸 🐵 🙊 🙉 🙊 🐒 🐔 🐧 🐦 🐤 🐣 🐥 🦆 🦩 🦅 🦉 🦇 🐺 🐗 🐴 🦄 🐝 🐛 🦋 🐌 🐚 🦗 🐞 🐜 🕷 🕸 🐢 🐍 🦎 🦂 🦀 🦑 🐙 🦐 🐠 🐟 🐡 🐬 🦈 🐳 🐋 🐊 🐆 🐅 🐃 🐂 🐄 🦌 🐪 🐫 🐘 🦏 🦍 🐎 🐖 🐐 🐏 🐑 🐕 🐩 🦮 🐕\u200D🦺 🐈 🐓 🦃 🕊 🐇 🐁 🐀 🐿 🦓 🦒 🦔 🦧 🦥 🦦 🦨 🦕 🦖 🦪 🐾 🐉 🐲 🌵 🎄 🌲 🌳 🌴 🌱 🌿 ☘️ 🍀 🎍 🎋 🍃 🍂 🍁 🍄 🌾 💐 🌷 🌹 🥀 🌻 🌼 🌸 🌺 🌎 🌍 🌏 🌕 🌖 🌗 🌘 🌑 🌒 🌓 🌔 🌚 🌝 🌞 🌛 🌜 🌙 🪐 💫 ⭐️ 🌟 ✨ ⚡️ 🔥 💥 ☄️ ☀️ 🌤 ⛅️ 🌥 🌦 🌈 ☁️ 🌧 ⛈ 🌩 🌨 ☃️ ⛄️ ❄️ 🌬 💨 🌪 🌫 🌊 💧 💦 ☔️\n🍏 🍎 🍐 🍊 🍋 🍌 🍉 🍇 🍓 🍈 🍒 🍑 🍍 🥝 🥑 🍅 🍆 🥒 🥕 🌽 🌶 🧄 🧅 🥔 🍠 🌰 🥜 🍯 🥐 🍞 🥖 🧀 🥚 🍳 🥓 🥞 🍤 🍗 🍖 🍕 🌭 🍔 🍟 🥙 🌮 🌯 🥗 🥘 🍝 🍜 🍲 🍥 🍣 🍱 🍛 🍚 🍙 🍘 🍢 🍡 🍧 🍨 🍦 🍰 🎂 🍮 🍭 🍬 🍫 🍿 🍩 🍪 🥛 🍼 ☕️ 🍵 🍶 🍺 🍻 🥂 🍷 🥃 🍸 🍹 🍾 🧃 🧉 🧊 🥄 🍴 🍽 🥥 🥨 🥩 🥪 🥣 🥫 🧇 🧆 🧈 🥟 🥠 🥡 🥧 🥤 🥢 \n🏀 🏈 ⚾️ 🎾 🏐 🏉 🎱 🏓 🏸 🥅 🏒 🏑 🏏 ⛳️ 🏹 🎣 🥊 🥋 ⛸ 🎿 ⛷ 🏂 🏋️\u200D♀️ 🏋️ 🤺 🤼\u200D♀️ 🤼\u200D♂️ 🤸\u200D♀️ 🤸\u200D♂️ ⛹️\u200D♀️ ⛹️ 🤾\u200D♀️ 🤾\u200D♂️ 🏌️\u200D♀️ 🏌️ 🏄\u200D♀️ 🏄 🏊\u200D♀️ 🏊 🤽\u200D♀️ 🤽\u200D♂️ 🚣\u200D♀️ 🚣 🏇 🚴\u200D♀️ 🚴 🚵\u200D♀️ 🚵 🪂 🎽 🏅 🎖 🥇 🥈 🥉 🏆 🏵 🎗 🎫 🎟 🎪 🤹\u200D♀️ 🤹\u200D♂️ 🎭 🎨 🎬 🎤 🎧 🎼 🎹 🥁 🎷 🎺 🎸 🎻 🪕 🎲 🎯 🎳 🎮 🎰 🛷 🥌 🪀 🪁\n🚗 🚕 🚙 🚌 🚎 🏎 🚓 🚑 🚒 🚐 🚚 🚛 🚜 🛴 🚲 🛵 🛺 🏍 🦽 🦼 🚨 🚔 🚍 🚘 🚖 🚡 🚠 🚟 🚃 🚋 🚞 🚝 🚄 🚅 🚈 🚂 🚆 🚇 🚊 🚉 🚁 🛩 ✈️ 🛫 🛬 🚀 🛰 💺 🛶 ⛵️ 🛥 🚤 🛳 ⛴ 🚢 ⚓️ 🚧 ⛽️ 🚏 🚦 🚥 🗺 🗿 🗽 ⛲️ 🗼 🏰 🏯 🏟 🎡 🎢 🎠 ⛱ 🏖 🏝 ⛰ 🏔 🗻 🌋 🏜 🏕 ⛺️ 🛤 🛣 🏗 🏭 🏠 🏡 🏘 🏚 🏢 🏬 🏣 🏤 🏥 🏦 🏨 🏪 🏫 🏩 💒 🏛 ⛪️ 🕌 🕍 🕋 🛕 ⛩ 🗾 🎑 🏞 🌅 🌄 🌠 🎇 🎆 🌇 🌆 🏙 🌃 🌌 🌉 🌁 🛸 ⌚️ 📱 📲 💻 ⌨️ 🖥 🖨 🖱 🖲 🕹 🗜 💽 💾 💿 📀 📼 📷 📸 📹 🎥 📽 🎞 📞 ☎️ 📟 📠 📺 📻 🎙 🎚 🎛 ⏱ ⏲ ⏰ 🕰 ⌛️ ⏳ 📡 🔋 🔌 💡 🔦 🕯 🗑 🛢 💸 💵 💴 💶 💷 💰 💳 💎 ⚖️ 🔧 🔨 ⚒ 🛠 ⛏ 🔩 ⚙️ ⛓ 🔫 💣 🔪 🗡 ⚔️ 🪓 🦯 🛡 🚬 ⚰️ ⚱️ 🏺 🔮 📿 💈 ⚗️ 🔭 🔬 🕳 💊 💉 🩸 🩹 🩺 🌡 🪒 🚽 🚰 🚿 🛁 🛀 🛎 🔑 🗝 🚪 🪑 🛋 🛏 🛌 🖼 🛍 🛒 🎁 🎈 🎏 🎀 🎊 🎉 🎎 🏮 🎐 ✉️ 📩 📨 📧 💌 📥 📤 📦 🏷 📪 📫 📬 📭 📮 📯 📜 📃 📄 📑 📊 📈 📉 🗒 🗓 📆 📅 📇 🗃 🗳 🗄 📋 📁 📂 🗂 🗞 📰 📓 📔 📒 📕 📗 📘 📙 📚 📖 🔖 🔗 📎 🖇 📐 📏 📌 📍 📌 🎌 🏳️ 🏴 🏁 🪔 ✂️ 🖊 🖋 ✒️ 🖌 🖍 📝 ✏️ 🔍 🔎 🔏 🔐 🔒 🔓\n❤️ 🧡 💛 💚 💙 💜 🖤 🤍 🤎 💔 ❣️ 💕 💞 💓 💗 💖 💘 💝 💟 ☮️ ✝️ ☪️ 🕉 ☸️ ✡️ 🔯 🕎 ☯️ ☦️ 🛐 ⛎ ♈️ ♉️ ♊️ ♋️ ♌️ ♍️ ♎️ ♏️ ♐️ ♑️ ♒️ ♓️ 🆔 ⚛️ 🉑 ☢️ ☣️ 📴 📳 🈶 🈚️ 🈸 🈺 🈷️ ✴️ 🆚 💮 🉐 ㊙️ ㊗️ 🈴 🈵 🈹 🈲 🅰️ 🅱️ 🆎 🆑 🅾️ 🆘 ❌ ⭕️ 🛑 ⛔️ 📛 🚫 💯 💢 ♨️ 🚷 🚯 🚳 🚱 🔞 📵 🚭 ❗️ ❕ ❓ ❔ ‼️ ⁉️ 🔅 🔆 〽️ ⚠️ 🚸 🔱 ⚜️ 🔰 ♻️ ✅ 🈯️ 💹 ❇️ ✳️ ❎ 🌐 💠 Ⓜ️ 🌀 💤 🏧 🚾 ♿️ 🅿️ 🈳 🈂️ 🛂 🛃 🛄 🛅 🚹 🚺 🚼 🚻 🚮 🎦 📶 🈁 🔣 ℹ️ 🔤 🔡 🔠 🆖 🆗 🆙 🆒 🆕 🆓 0️⃣ 1️⃣ 2️⃣ 3️⃣ 4️⃣ 5️⃣ 6️⃣ 7️⃣ 8️⃣ 9️⃣ 🔟 🔢 #️⃣ *️⃣ ▶️ ⏸ ⏯ ⏹ ⏺ ⏭ ⏮ ⏩ ⏪ ⏫ ⏬ ◀️ 🔼 🔽 ➡️ ⬅️ ⬆️ ⬇️ ↗️ ↘️ ↙️ ↖️ ↕️ ↔️ ↪️ ↩️ ⤴️ ⤵️ 🔀 🔁 🔂 🔄 🔃 🎵 🎶 ➕ ➖ ➗ ✖️ 💲 💱 ™️ ©️ ®️ 〰️ ➰ ➿ 🔚 🔙 🔛 🔝 ✔️ ☑️ 🔘 🔴 🟠 🟡 🟢 🔵 🟣 ⚫️ ⚪️ 🟤 🔺 🔻 🔸 🔹 🔶 🔷 🔳 🔲 ▪️ ▫️ ◾️ ◽️ ◼️ ◻️ ⬛️ ⬜️ 🟥 🟧 🟨 🟩 🟦 🟪 🟫 🔈 🔇 🔉 🔊 🔔 🔕 📣 📢 👁\u200D🗨 💬 💭 🗯 ♠️ ♣️ ♥️ ♦️ 🃏 🎴 🀄️ 🕐 🕑 🕒 🕓 🕔 🕕 🕖 🕗 🕘 🕙 🕚 🕛 🕜 🕝 🕞 🕟 🕠 🕡 🕢 🕣 🕤 🕥 🕦 🕧 ⏏ ♀ ♂ ⚕ ♾️ 🏳️\u200D🌈🇺🇳🇦🇫🏴\u200D☠️🏁🇦🇽🇦🇱🇦🇮🇦🇴🇦🇩🇦🇸🇩🇿🇦🇶🇦🇬🇦🇷🇦🇲🇦🇼🇧🇭🇧🇸🇦🇿🇦🇹🇦🇺🇧🇩🇧🇧🇧🇾🇧🇪🇧🇿🇧🇯🇧🇲🇧🇹🇧🇴🇧🇦🇧🇼🇧🇷🇮🇴🇻🇬🇧🇳🇧🇬🇧🇫🇧🇮🇰🇭🇨🇲🇨🇦🇮🇨🇨🇻🇧🇶🇰🇾🇨🇨🇹🇩🇨🇱🇨🇳🇨🇽🇨🇨🇨🇴🇰🇲🇨🇬🇨🇩🇨🇰🇨🇮🇨🇷🇭🇷🇨🇺🇨🇼🇨🇾🇪🇨🇨🇿🇩🇰🇩🇯🇸🇻🇪🇬🇪🇨🇩🇴🏳️\u200D🌈🏳️\u200D🌈🏳️\u200D🌈🏳️\u200D🌈🏳️\u200D🌈🏳️\u200D🌈🏳️\u200D🌈🏳️\u200D🌈🏳️\u200D🌈🏳️\u200D🌈🏳️\u200D🌈🏳️\u200D🌈🏳️\u200D🌈🏳️\u200D🌈🏳️\u200D🌈🏳️\u200D🌈🏳️\u200D🌈","userName":"P u n k P r i n c e s s"}},{"id":"6177363055","type":"user-reviews","attributes":{"isEdited":false,"date":"2020-07-09T16:26:33Z","title":"std","rating":1,"review":"this app gave me an std","userName":"tihs tae"}}]}