{"next":"/v1/catalog/us/apps/1135325440/reviews?l=en-US&offset=94930","data":[{"id":"6177582467","type":"user-reviews","attributes":{"rating":1,"isEdited":false,"date":"2020-07-09T17:33:12Z","review":"this app is terribly made. it is always kicking you out and glitching very bad.","userName":"angryteen12367","title":"terribly made app"}},{"id":"6177566126","type":"user-reviews","attributes":{"rating":1,"isEdited":false,"date":"2020-07-09T17:27:55Z","review":"Imagine supporting a monster","userName":"Your_Wallet","title":"."}},{"id":"6177559650","type":"user-reviews","attributes":{"rating":1,"isEdited":false,"date":"2020-07-09T17:25:51Z","review":"It’s a bad app","userName":"rockthing123","title":"I don’t like this app"}},{"id":"6177556874","type":"user-reviews","attributes":{"rating":1,"isEdited":false,"date":"2020-07-09T17:25:00Z","review":"I came from tik tok and i’m part of gen z y’all","userName":"ndjsijc","title":"Tik tok✨"}},{"id":"6177534318","type":"user-reviews","attributes":{"rating":1,"isEdited":false,"date":"2020-07-09T17:17:56Z","review":"Lets get this trash app out of the App Store","userName":"p64trick","title":"Tiktok"}},{"id":"6177501075","type":"user-reviews","attributes":{"rating":1,"isEdited":false,"date":"2020-07-09T17:07:34Z","review":"Likely modeled after Trump’s first term","userName":"Jim Jim Johnson","title":"Terrible App"}},{"id":"6177493476","type":"user-reviews","attributes":{"rating":1,"isEdited":false,"date":"2020-07-09T17:05:17Z","review":"hated it... would not recommend getting.","userName":"Maizeniya617","title":"🥱🥱"}},{"id":"6177471330","type":"user-reviews","attributes":{"rating":1,"isEdited":false,"date":"2020-07-09T16:58:38Z","review":"I hate it","userName":"GG Tycch","title":"disgusting I hate it"}},{"id":"6177467591","type":"user-reviews","attributes":{"rating":1,"isEdited":false,"date":"2020-07-09T16:57:34Z","review":"he made this app from scratch🧚🧚💕 now let’s take it down","userName":"Lebron8225","title":"good try !!"}},{"id":"6177465673","type":"user-reviews","attributes":{"rating":1,"isEdited":false,"date":"2020-07-09T16:57:01Z","review":"This app caused me to develop brain damage","userName":"proooo sportssss","title":"Trash"}}]}