{"next":"/v1/catalog/us/apps/1135325440/reviews?l=en-US&offset=109350","data":[{"id":"6174822046","type":"user-reviews","attributes":{"rating":1,"isEdited":false,"date":"2020-07-09T03:13:49Z","title":"rip archie","userName":"Gabby Tejeda","review":"this app killed my dog"}},{"id":"6174818977","type":"user-reviews","attributes":{"rating":1,"isEdited":false,"date":"2020-07-09T03:12:54Z","title":"Trash","userName":"lizzzzzxxy","review":"Trash"}},{"id":"6174785796","type":"user-reviews","attributes":{"rating":1,"isEdited":false,"date":"2020-07-09T03:03:02Z","title":"Trash","userName":"yjsdovhsk","review":"Trash"}},{"id":"6174777130","type":"user-reviews","attributes":{"rating":1,"isEdited":false,"date":"2020-07-09T03:00:22Z","title":":)","userName":"its awsome but...","review":"According to all known laws\nof aviation,\n\n  \nthere is no way a bee\nshould be able to fly.\n\n  \nIts wings are too small to get\nits fat little body off the ground.\n\n  \nThe bee, of course, flies anyway\n\n  \nbecause bees don't care\nwhat humans think is impossible.\n\n  \nYellow, black. Yellow, black.\nYellow, black. Yellow, black.\n\n  \nOoh, black and yellow!\nLet's shake it up a little.\n\n  \nBarry! Breakfast is ready!\n\n  \nOoming!\n\n  \nHang on a second.\n\n  \nHello?\n\n  \n- Barry?\n- Adam?\n\n  \n- Oan you believe this is happening?\n- I can't. I'll pick you up.\n\n  \nLooking sharp.\n\n  \nUse the stairs. Your father\npaid good money for those.\n\n  \nSorry. I'm excited.\n\n  \nHere's the graduate.\nWe're very proud of you, son.\n\n  \nA perfect report card, all B's.\n\n  \nVery proud.\n\n  \nMa! I got a thing going here.\n\n  \n- You got lint on your fuzz.\n- Ow! That's me!\n\n  \n- Wave to us! We'll be in row 118,000.\n- Bye!\n\n  \nBarry, I told you,\nstop flying in the house!\n\n  \n- Hey, Adam.\n- Hey, Barry.\n\n  \n- Is that fuzz gel?\n- A little. Special day, graduation.\n\n  \nNever thought I'd make it.\n\n  \nThree days grade school,\nthree days high school.\n\n  \nThose were awkward.\n\n  \nThree days college. I'm glad I took\na day and hitchhiked around the hive.\n\n  \nYou did come back different.\n\n  \n- Hi, Barry.\n- Artie, growing a mustache? Looks good.\n\n  \n- Hear about Frankie?\n- Yeah.\n\n  \n- You going to the funeral?\n- No, I'm not going.\n\n  \nEverybody knows,\nsting someone, you die.\n\n  \nDon't waste it on a squirrel.\nSuch a hothead.\n\n  \nI guess he could have\njust gotten out of the way.\n\n  \nI love this incorporating\nan amusement park into our day."}},{"id":"6174752161","type":"user-reviews","attributes":{"rating":1,"isEdited":false,"date":"2020-07-09T02:52:45Z","title":"no worth it","userName":"iiiiammmbeckyyyy","review":"bad"}},{"id":"6174748403","type":"user-reviews","attributes":{"rating":1,"isEdited":false,"date":"2020-07-09T02:51:36Z","title":"Terrible app","userName":"Sean._s","review":"Politics bad ice cream good"}},{"id":"6174739415","type":"user-reviews","attributes":{"rating":1,"isEdited":false,"date":"2020-07-09T02:48:53Z","title":"TikTok","userName":"Spanky43111111111111111111","review":"Please don’t take away TikTok Oh and BLM🧚🏾🤩🥰🤪😌"}},{"id":"6174730478","type":"user-reviews","attributes":{"rating":1,"isEdited":false,"date":"2020-07-09T02:46:08Z","title":"THIS APP IS HORRIBLE DO NOT DOWNLOAD!!!","userName":"love9873527362719","review":"This app made my phone explode."}},{"id":"6174728598","type":"user-reviews","attributes":{"rating":1,"isEdited":false,"date":"2020-07-09T02:45:35Z","title":"ew","userName":"dhkebdje","review":"absolutely horrible"}},{"id":"6174700187","type":"user-reviews","attributes":{"rating":1,"isEdited":false,"date":"2020-07-09T02:37:03Z","title":"not what i was expecting.","userName":"Taki girl looking 4 A bf","review":"who’s this cute cheeto 👁👄👁"}}]}