{"next":"/v1/catalog/us/apps/1135325440/reviews?l=en-US&offset=96690","data":[{"id":"6176820381","type":"user-reviews","attributes":{"review":"Terrible, awful, scary.","rating":1,"userName":"Perpjase","title":"Bad","date":"2020-07-09T13:57:13Z","isEdited":false}},{"id":"6176815710","type":"user-reviews","attributes":{"review":"i don’t get the app like i just don’t it almost killed me and my dogs vomited","rating":1,"userName":"you wish i were healther","title":"karen","date":"2020-07-09T13:55:59Z","isEdited":false}},{"id":"6176806800","type":"user-reviews","attributes":{"review":"The worst app ever-fitting because Trump is the worst president ever","rating":1,"userName":"B.B. GMA","title":"The worst","date":"2020-07-09T13:53:36Z","isEdited":false}},{"id":"6176786905","type":"user-reviews","attributes":{"review":"TOOK 45 WEEKS AND ALL I WANTED TO DO AS SUPPORT OUR BELOVED PRESIDENT! Do NOT recommend at all, trust me!","rating":1,"userName":"barbs✨💅","title":"Don’t download, waste of time","date":"2020-07-09T13:48:22Z","isEdited":false}},{"id":"6176767451","type":"user-reviews","attributes":{"review":"This took DAYS to download it was really racist and homophobic I HATED IT don’t download it","rating":1,"userName":"camprockfanatic","title":"DONT DOWNLOAD","date":"2020-07-09T13:43:09Z","isEdited":false}},{"id":"6176741126","type":"user-reviews","attributes":{"review":"this is disgusting i can’t believe i downloaded it this is so bad delete it  now","rating":1,"userName":"liahixson","title":"ew","date":"2020-07-09T13:36:17Z","isEdited":false}},{"id":"6176709556","type":"user-reviews","attributes":{"review":"bad ideas","rating":1,"userName":"lover234❤","title":"horrible","date":"2020-07-09T13:27:59Z","isEdited":false}},{"id":"6176674668","type":"user-reviews","attributes":{"review":"Worse app ever nothing works and its always bugging out and closing its self. DO NOT DOWLOAD IT EILL GLITCH YOUR PUONE OUT.","rating":1,"userName":"42069noice!","title":"WORST APP EVER","date":"2020-07-09T13:18:46Z","isEdited":false}},{"id":"6176668238","type":"user-reviews","attributes":{"review":"So bad one star","rating":1,"userName":"donotbantiktokitdoesntstopus","title":"Didnt work and gen z is cool","date":"2020-07-09T13:17:03Z","isEdited":false}},{"id":"6176523505","type":"user-reviews","attributes":{"review":"Terrible. No app worse.","rating":1,"userName":"Hello buddies","title":"Horrid","date":"2020-07-09T12:38:03Z","isEdited":false}}]}