{"next":"/v1/catalog/us/apps/1135325440/reviews?l=en-US&offset=107550","data":[{"id":"6173641319","type":"user-reviews","attributes":{"date":"2020-07-08T20:35:07Z","title":"delete this app","rating":1,"isEdited":false,"userName":"nevercan bantiktok","review":"garbage"}},{"id":"6173627256","type":"user-reviews","attributes":{"date":"2020-07-08T20:30:04Z","title":"Tiktok","rating":1,"isEdited":false,"userName":"THE AMAZING ORANGE","review":"The orange wants to get rid of tiktok so get rekted"}},{"id":"6173612326","type":"user-reviews","attributes":{"date":"2020-07-08T20:24:46Z","title":"Trash","rating":1,"isEdited":false,"userName":"fucdtrump","review":"This app is trash."}},{"id":"6173582236","type":"user-reviews","attributes":{"date":"2020-07-08T20:14:10Z","title":"GIVING OFF HORRIBLE ENERGY","rating":1,"isEdited":false,"userName":"Juzt me guys","review":"THE APP IS GLITCHING ALOT. JUST HAVING THE APP ON MY PHONE BRINGS THE ROACHES OUT AND ITS DISGUSTING. ALSO I KEEP SEEING THE ORANGE ORANGUTAN called Donald Trump on my screen it’s very unethical in my opinion"}},{"id":"6173561372","type":"user-reviews","attributes":{"date":"2020-07-08T20:06:58Z","title":"worst app ever","rating":1,"isEdited":false,"userName":"TheKatherineFaith","review":"If"}},{"id":"6173546926","type":"user-reviews","attributes":{"date":"2020-07-08T20:02:06Z","title":"THE WORST!!!!","rating":1,"isEdited":false,"userName":"mads421","review":"horrible worst app ever stinky poo poo app made by a stinky poo poo man"}},{"id":"6173524946","type":"user-reviews","attributes":{"date":"2020-07-08T19:54:39Z","title":"awful app","rating":1,"isEdited":false,"userName":"trans rights are human rights","review":"honestly the worst thing ever \n\nhow could anyone support a white supremacist for not one but two terms \n\nDUMP TRUMP\nBLACK LIVES MATTER\nACAB\nHELP MISSING AND MURDERED INDIGENOUS WOMEN\nLOVE IS LOVE \nDEFUND THE POLICE \nNO ONE IS ILLEGAL ON STOLEN LAND"}},{"id":"6173502940","type":"user-reviews","attributes":{"date":"2020-07-08T19:47:01Z","title":"really bad","rating":1,"isEdited":false,"userName":"Khuska","review":"doesnt fit my vibe and aesthetic"}},{"id":"6173500222","type":"user-reviews","attributes":{"date":"2020-07-08T19:46:07Z","title":"discostang","rating":1,"isEdited":false,"userName":"HeroNali~","review":"this app is the worst thing since jeffrey epstein"}},{"id":"6173475061","type":"user-reviews","attributes":{"date":"2020-07-08T19:37:28Z","title":"it's bad","rating":1,"isEdited":false,"userName":"nejdkgkdjsnd","review":"(insert the whole bee movie script here)"}}]}